<?xml version="1.0"?>
<opencv_storage>
<ESMBLGLMaxSum type_id="opencv-matrix">
  <rows>10</rows>
  <cols>10</cols>
  <dt>d</dt>
  <data>
    50. 0. 0. 0. 0. 0. 0. 0. 0. 0. 0. 50. 0. 0. 0. 0. 0. 0. 0. 0. 0. 0.
    50. 0. 0. 0. 0. 0. 0. 0. 0. 0. 0. 50. 0. 0. 0. 0. 0. 0. 0. 0. 0. 0.
    50. 0. 0. 0. 0. 0. 0. 0. 0. 0. 0. 19. 8. 0. 23. 0. 0. 0. 0. 0. 0. 0.
    50. 0. 0. 0. 0. 0. 2. 0. 0. 0. 0. 48. 0. 0. 2. 0. 0. 0. 0. 0. 0. 0.
    48. 0. 0. 0. 0. 0. 0. 0. 0. 0. 0. 50.</data></ESMBLGLMaxSum>
</opencv_storage>
